lync/__init__.py
lync/cli.py
lync/client.py
lync/exceptions.py
lync/py.typed
lync/types.py
lync/utils.py
lync-1.0.0.dist-info/licenses/LICENSE
lync-1.0.0.dist-info/METADATA
lync-1.0.0.dist-info/WHEEL
lync-1.0.0.dist-info/entry_points.txt
lync-1.0.0.dist-info/top_level.txt
lync-1.0.0.dist-info/RECORD
