Metadata-Version: 2.4
Name: lync
Version: 1.0.0
Summary: Cross-platform attribution tracking for web and mobile apps
Home-page: https://lync.so
Author: Lync.so
Author-email: "Lync.so" <support@lync.so>
License: MIT
Project-URL: Homepage, https://lync.so
Project-URL: Documentation, https://docs.lync.so
Project-URL: Repository, https://github.com/lync-so/lync-sdk
Project-URL: Bug Tracker, https://github.com/lync-so/lync-sdk/issues
Keywords: attribution,tracking,analytics,marketing,conversion,fingerprinting,lync,cross-platform
Classifier: Development Status :: 5 - Production/Stable
Classifier: Intended Audience :: Developers
Classifier: License :: OSI Approved :: MIT License
Classifier: Operating System :: OS Independent
Classifier: Programming Language :: Python :: 3
Classifier: Programming Language :: Python :: 3.7
Classifier: Programming Language :: Python :: 3.8
Classifier: Programming Language :: Python :: 3.9
Classifier: Programming Language :: Python :: 3.10
Classifier: Programming Language :: Python :: 3.11
Classifier: Programming Language :: Python :: 3.12
Classifier: Topic :: Software Development :: Libraries :: Python Modules
Classifier: Topic :: Internet :: WWW/HTTP
Classifier: Topic :: System :: Monitoring
Classifier: Topic :: Office/Business
Requires-Python: >=3.7
License-File: LICENSE
Requires-Dist: requests>=2.25.0
Requires-Dist: typing-extensions>=4.0.0; python_version < "3.8"
Provides-Extra: dev
Requires-Dist: pytest>=6.0; extra == "dev"
Requires-Dist: pytest-cov>=2.10; extra == "dev"
Requires-Dist: black>=21.0; extra == "dev"
Requires-Dist: isort>=5.0; extra == "dev"
Requires-Dist: mypy>=0.900; extra == "dev"
Requires-Dist: flake8>=3.8; extra == "dev"
Provides-Extra: flask
Requires-Dist: flask>=1.0; extra == "flask"
Provides-Extra: django
Requires-Dist: django>=2.2; extra == "django"
Provides-Extra: fastapi
Requires-Dist: fastapi>=0.60.0; extra == "fastapi"
Dynamic: author
Dynamic: home-page
Dynamic: license-file
Dynamic: requires-python
